pygfssss/GF256elt.py
pygfssss/PGF256.py
pygfssss/PGF256Interpolator.py
pygfssss/__init__.py
pygfssss/core.py
pygfssss/gfcombine.py
pygfssss/gfsplit.py
pygfssss/gfssss.py
pygfssss/test_PySSSS.py
pygfssss/test_gfcombine_gfsplit.py
pygfssss/test_gfssss.py
pygfssss-1.0.1.dist-info/LICENSE
pygfssss-1.0.1.dist-info/METADATA
pygfssss-1.0.1.dist-info/WHEEL
pygfssss-1.0.1.dist-info/entry_points.txt
pygfssss-1.0.1.dist-info/top_level.txt
pygfssss-1.0.1.dist-info/RECORD
