Metadata-Version: 2.1
Name: pygfssss
Version: 1.0.1
Summary: Python implementation of Shamir's Secret Sharing Scheme, using polynomials over GF(256)
Home-page: https://github.com/trianglee/pygfssss
Author: Nimrod Zimerman
Author-email: zimerman@fastmail.fm
License: Apache License 2.0
Platform: UNKNOWN
Requires-Python: >=3.7
